malwaretl_stoq_transformer/__init__.py
malwaretl_stoq_transformer/transformer.py
malwaretl_stoq_transformer-1.0.7.dist-info/LICENSE
malwaretl_stoq_transformer-1.0.7.dist-info/METADATA
malwaretl_stoq_transformer-1.0.7.dist-info/WHEEL
malwaretl_stoq_transformer-1.0.7.dist-info/top_level.txt
malwaretl_stoq_transformer-1.0.7.dist-info/RECORD
