Metadata-Version: 2.1
Name: malwaretl-stoq-transformer
Version: 1.0.7
Summary: Helper class to build Stoq instances for use in MalwareETL pipelines
Home-page: https://github.com/g-clef/stoq_transformer
Author: Aaron Gee-Clough
Author-email: aaron@g-clef.net
Project-URL: Bug Tracker, https://github.com/g-clef/stoq_transformer/issues
Classifier: Programming Language :: Python :: 3
Classifier: License :: OSI Approved :: Apache Software License
Classifier: Operating System :: OS Independent
Requires-Python: >=3.6
License-File: LICENSE
Requires-Dist: stoq-framework
Requires-Dist: lief (==0.11.5)
